parity_tensor/__init__.py
parity_tensor/_version.py
parity_tensor/parity_tensor.py
parity_tensor/version.py
parity_tensor-0.0.1a14.dist-info/METADATA
parity_tensor-0.0.1a14.dist-info/WHEEL
parity_tensor-0.0.1a14.dist-info/top_level.txt
parity_tensor-0.0.1a14.dist-info/RECORD
