Metadata-Version: 2.4
Name: parity_tensor
Version: 0.0.1a14
Summary: A parity tensor package
Author-email: Hao Zhang <hzhangxyz@outlook.com>
License-Expression: GPL-3.0-or-later
Requires-Python: >=3
Requires-Dist: torch
Provides-Extra: dev
Requires-Dist: yapf; extra == "dev"
Requires-Dist: pylint; extra == "dev"
Requires-Dist: mypy; extra == "dev"
Requires-Dist: pytest; extra == "dev"
Requires-Dist: pytest-cov; extra == "dev"
